sifima/__init__.py
sifima-0.26.dist-info/LICENSE
sifima-0.26.dist-info/METADATA
sifima-0.26.dist-info/WHEEL
sifima-0.26.dist-info/top_level.txt
sifima-0.26.dist-info/RECORD
