Metadata-Version: 2.1
Name: sifima
Version: 0.26
Summary: This is a project to work with files
Home-page: https://vk.com/gerod241
Author: Gerod
Author-email: maksd241@gmail.com
License: UNKNOWN
Platform: UNKNOWN
Classifier: Programming Language :: Python :: 3
Classifier: License :: OSI Approved :: MIT License
Classifier: Operating System :: OS Independent
